{
  "ticker": "BHLB",
  "name": "Berkshire Hills Bancorp, Inc.",
  "sector": "Financial Services",
  "market_cap": 1133949312.0,
  "source_list": "AltScreen",
  "fundamentals": {
    "PE": 9.953252,
    "PB": 0.93493456,
    "EV_Revenue": 2.408,
    "ROE": 0.09689999,
    "ProfitMargin": 0.24781999,
    "GrossMargin": 0.0,
    "DividendYield": 2.91
  },
  "technical_indicators": {
    "RSI_14": 41.29638063734656,
    "Momentum_10": -7.708254893952353,
    "MACD": -0.0727873380417953,
    "BB_Percent": 0.1025534302792861,
    "SMA20_above_SMA50": 1.0
  },
  "scores": {
    "ValueScore": 0.9347139143550192,
    "QualityScore": 0.3973851354554842,
    "SignalScore": 0.5763022202403167
  },
  "volatility": 0.0173557374791307,
  "beta": 0.621,
  "return_6m": -0.1928107723220922,
  "analyst_rating": {
    "recommendation": "none",
    "analyst_count": 5,
    "target_mean_price": 32.1
  },
  "visual_data": {
    "sparkline": [
      {
        "date": "2024-12-02",
        "price": 30.73
      },
      {
        "date": "2024-12-03",
        "price": 30.32
      },
      {
        "date": "2024-12-04",
        "price": 30.65
      },
      {
        "date": "2024-12-05",
        "price": 30.4
      },
      {
        "date": "2024-12-06",
        "price": 30.75
      },
      {
        "date": "2024-12-09",
        "price": 30.37
      },
      {
        "date": "2024-12-10",
        "price": 30.31
      },
      {
        "date": "2024-12-11",
        "price": 30.61
      },
      {
        "date": "2024-12-12",
        "price": 30.26
      },
      {
        "date": "2024-12-13",
        "price": 30.2
      },
      {
        "date": "2024-12-16",
        "price": 29.87
      },
      {
        "date": "2024-12-17",
        "price": 29.13
      },
      {
        "date": "2024-12-18",
        "price": 28.12
      },
      {
        "date": "2024-12-19",
        "price": 27.8
      },
      {
        "date": "2024-12-20",
        "price": 28.58
      },
      {
        "date": "2024-12-23",
        "price": 28.6
      },
      {
        "date": "2024-12-24",
        "price": 28.66
      },
      {
        "date": "2024-12-26",
        "price": 28.66
      },
      {
        "date": "2024-12-27",
        "price": 28.3
      },
      {
        "date": "2024-12-30",
        "price": 28.23
      },
      {
        "date": "2024-12-31",
        "price": 28.43
      },
      {
        "date": "2025-01-02",
        "price": 27.94
      },
      {
        "date": "2025-01-03",
        "price": 28.22
      },
      {
        "date": "2025-01-06",
        "price": 28.0
      },
      {
        "date": "2025-01-07",
        "price": 27.84
      },
      {
        "date": "2025-01-08",
        "price": 27.89
      },
      {
        "date": "2025-01-10",
        "price": 27.26
      },
      {
        "date": "2025-01-13",
        "price": 27.47
      },
      {
        "date": "2025-01-14",
        "price": 28.22
      },
      {
        "date": "2025-01-15",
        "price": 28.57
      },
      {
        "date": "2025-01-16",
        "price": 28.5
      },
      {
        "date": "2025-01-17",
        "price": 28.5
      },
      {
        "date": "2025-01-21",
        "price": 28.72
      },
      {
        "date": "2025-01-22",
        "price": 28.2
      },
      {
        "date": "2025-01-23",
        "price": 28.21
      },
      {
        "date": "2025-01-24",
        "price": 28.32
      },
      {
        "date": "2025-01-27",
        "price": 28.65
      },
      {
        "date": "2025-01-28",
        "price": 28.83
      },
      {
        "date": "2025-01-29",
        "price": 28.57
      },
      {
        "date": "2025-01-30",
        "price": 29.13
      },
      {
        "date": "2025-01-31",
        "price": 29.41
      },
      {
        "date": "2025-02-03",
        "price": 28.94
      },
      {
        "date": "2025-02-04",
        "price": 29.9
      },
      {
        "date": "2025-02-05",
        "price": 30.07
      },
      {
        "date": "2025-02-06",
        "price": 30.48
      },
      {
        "date": "2025-02-07",
        "price": 30.05
      },
      {
        "date": "2025-02-10",
        "price": 29.65
      },
      {
        "date": "2025-02-11",
        "price": 30.18
      },
      {
        "date": "2025-02-12",
        "price": 29.51
      },
      {
        "date": "2025-02-13",
        "price": 29.58
      },
      {
        "date": "2025-02-14",
        "price": 29.38
      },
      {
        "date": "2025-02-18",
        "price": 29.47
      },
      {
        "date": "2025-02-19",
        "price": 29.21
      },
      {
        "date": "2025-02-20",
        "price": 28.61
      },
      {
        "date": "2025-02-21",
        "price": 28.06
      },
      {
        "date": "2025-02-24",
        "price": 27.9
      },
      {
        "date": "2025-02-25",
        "price": 28.27
      },
      {
        "date": "2025-02-26",
        "price": 28.24
      },
      {
        "date": "2025-02-27",
        "price": 28.12
      },
      {
        "date": "2025-02-28",
        "price": 28.49
      },
      {
        "date": "2025-03-03",
        "price": 28.11
      },
      {
        "date": "2025-03-04",
        "price": 26.97
      },
      {
        "date": "2025-03-05",
        "price": 27.07
      },
      {
        "date": "2025-03-06",
        "price": 26.67
      },
      {
        "date": "2025-03-07",
        "price": 26.48
      },
      {
        "date": "2025-03-10",
        "price": 25.76
      },
      {
        "date": "2025-03-11",
        "price": 25.88
      },
      {
        "date": "2025-03-12",
        "price": 26.05
      },
      {
        "date": "2025-03-13",
        "price": 25.75
      },
      {
        "date": "2025-03-14",
        "price": 26.28
      },
      {
        "date": "2025-03-17",
        "price": 26.15
      },
      {
        "date": "2025-03-18",
        "price": 26.32
      },
      {
        "date": "2025-03-19",
        "price": 26.33
      },
      {
        "date": "2025-03-20",
        "price": 26.25
      },
      {
        "date": "2025-03-21",
        "price": 26.12
      },
      {
        "date": "2025-03-24",
        "price": 26.92
      },
      {
        "date": "2025-03-25",
        "price": 26.66
      },
      {
        "date": "2025-03-26",
        "price": 26.72
      },
      {
        "date": "2025-03-27",
        "price": 26.62
      },
      {
        "date": "2025-03-28",
        "price": 26.15
      },
      {
        "date": "2025-03-31",
        "price": 26.09
      },
      {
        "date": "2025-04-01",
        "price": 26.09
      },
      {
        "date": "2025-04-02",
        "price": 26.21
      },
      {
        "date": "2025-04-03",
        "price": 24.25
      },
      {
        "date": "2025-04-04",
        "price": 23.54
      },
      {
        "date": "2025-04-07",
        "price": 23.59
      },
      {
        "date": "2025-04-08",
        "price": 23.11
      },
      {
        "date": "2025-04-09",
        "price": 24.27
      },
      {
        "date": "2025-04-10",
        "price": 22.98
      },
      {
        "date": "2025-04-11",
        "price": 22.9
      },
      {
        "date": "2025-04-14",
        "price": 23.15
      },
      {
        "date": "2025-04-15",
        "price": 23.56
      },
      {
        "date": "2025-04-16",
        "price": 23.47
      },
      {
        "date": "2025-04-17",
        "price": 23.63
      },
      {
        "date": "2025-04-21",
        "price": 23.35
      },
      {
        "date": "2025-04-22",
        "price": 23.94
      },
      {
        "date": "2025-04-23",
        "price": 24.3
      },
      {
        "date": "2025-04-24",
        "price": 25.08
      },
      {
        "date": "2025-04-25",
        "price": 24.68
      },
      {
        "date": "2025-04-28",
        "price": 24.9
      },
      {
        "date": "2025-04-29",
        "price": 25.12
      },
      {
        "date": "2025-04-30",
        "price": 24.83
      },
      {
        "date": "2025-05-01",
        "price": 25.09
      },
      {
        "date": "2025-05-02",
        "price": 25.61
      },
      {
        "date": "2025-05-05",
        "price": 25.66
      },
      {
        "date": "2025-05-06",
        "price": 25.29
      },
      {
        "date": "2025-05-07",
        "price": 25.29
      },
      {
        "date": "2025-05-08",
        "price": 25.69
      },
      {
        "date": "2025-05-09",
        "price": 25.54
      },
      {
        "date": "2025-05-12",
        "price": 26.55
      },
      {
        "date": "2025-05-13",
        "price": 26.78
      },
      {
        "date": "2025-05-14",
        "price": 26.56
      },
      {
        "date": "2025-05-15",
        "price": 26.78
      },
      {
        "date": "2025-05-16",
        "price": 26.53
      },
      {
        "date": "2025-05-19",
        "price": 26.36
      },
      {
        "date": "2025-05-20",
        "price": 26.27
      },
      {
        "date": "2025-05-21",
        "price": 25.28
      },
      {
        "date": "2025-05-22",
        "price": 25.09
      },
      {
        "date": "2025-05-23",
        "price": 24.83
      },
      {
        "date": "2025-05-27",
        "price": 25.4
      },
      {
        "date": "2025-05-28",
        "price": 24.95
      },
      {
        "date": "2025-05-29",
        "price": 25.09
      },
      {
        "date": "2025-05-30",
        "price": 24.76
      },
      {
        "date": "2025-06-02",
        "price": 24.42
      }
    ],
    "current_price_data": {
      "price": 24.43,
      "change": -0.36,
      "percent_change": -1.45
    }
  },
  "news_sentiment": {
    "summary": "Les titres concernent Berkshire Hills Bancorp, Inc. (NYSE:BHLB), une banque de d\u00e9p\u00f4t et de pr\u00eat am\u00e9ricaine. Les articles traitent d'analyses financi\u00e8res, d'investissements, de renseignements sur les ventes de parts et les prises de participation. Les titres pr\u00e9sentent des signaux positifs, notamment l'investissement de Jefferies Financial Group et l'approbation de certains projets \u00e0 la r\u00e9union annuelle de l'entreprise. Les titres n'indiquent pas d'\u00e9v\u00e9nements marquants, mais la date de publication des r\u00e9sultats cl\u00e9s pour la premi\u00e8re trimestre 202",
    "sentiment_score": 0.1,
    "label": "POSITIVE",
    "positive_ratio": 0.1,
    "neutral_ratio": 0.9,
    "negative_ratio": 0.0,
    "bullet_positive_count": 0,
    "bullet_negative_count": 0,
    "headlines": []
  },
  "extraction_date": "2025-06-02"
}