{
  "ticker": "CACI",
  "name": "CACI International, Inc.",
  "sector": "Technology",
  "market_cap": 9102142464.0,
  "source_list": "AltScreen",
  "fundamentals": {
    "PE": 19.533743,
    "PB": 2.4570818,
    "EV_Revenue": 1.515,
    "ROE": 0.13484,
    "ProfitMargin": 0.056999996,
    "GrossMargin": 0.33271,
    "DividendYield": null
  },
  "technical_indicators": {
    "RSI_14": 31.517378559626607,
    "Momentum_10": -13.61368700817354,
    "MACD": -0.8039911437828096,
    "BB_Percent": -0.1661294067716612,
    "SMA20_above_SMA50": 1.0
  },
  "scores": {
    "ValueScore": 0.9316464344914324,
    "QualityScore": 0.4264843420567897,
    "SignalScore": 0.6685427077308888
  },
  "volatility": 0.0247845885502011,
  "beta": 0.644,
  "return_6m": -0.0995670751388723,
  "analyst_rating": {
    "recommendation": "buy",
    "analyst_count": 15,
    "target_mean_price": 498.02133
  },
  "visual_data": {
    "sparkline": [
      {
        "date": "2024-12-02",
        "price": 459.69
      },
      {
        "date": "2024-12-03",
        "price": 453.9
      },
      {
        "date": "2024-12-04",
        "price": 454.0
      },
      {
        "date": "2024-12-05",
        "price": 456.15
      },
      {
        "date": "2024-12-06",
        "price": 454.52
      },
      {
        "date": "2024-12-09",
        "price": 437.19
      },
      {
        "date": "2024-12-10",
        "price": 444.49
      },
      {
        "date": "2024-12-11",
        "price": 430.0
      },
      {
        "date": "2024-12-12",
        "price": 414.0
      },
      {
        "date": "2024-12-13",
        "price": 409.91
      },
      {
        "date": "2024-12-16",
        "price": 416.95
      },
      {
        "date": "2024-12-17",
        "price": 415.14
      },
      {
        "date": "2024-12-18",
        "price": 403.33
      },
      {
        "date": "2024-12-19",
        "price": 399.93
      },
      {
        "date": "2024-12-20",
        "price": 402.72
      },
      {
        "date": "2024-12-23",
        "price": 405.02
      },
      {
        "date": "2024-12-24",
        "price": 404.88
      },
      {
        "date": "2024-12-26",
        "price": 408.03
      },
      {
        "date": "2024-12-27",
        "price": 406.17
      },
      {
        "date": "2024-12-30",
        "price": 402.23
      },
      {
        "date": "2024-12-31",
        "price": 404.06
      },
      {
        "date": "2025-01-02",
        "price": 410.96
      },
      {
        "date": "2025-01-03",
        "price": 420.14
      },
      {
        "date": "2025-01-06",
        "price": 415.11
      },
      {
        "date": "2025-01-07",
        "price": 413.95
      },
      {
        "date": "2025-01-08",
        "price": 415.91
      },
      {
        "date": "2025-01-10",
        "price": 431.24
      },
      {
        "date": "2025-01-13",
        "price": 446.06
      },
      {
        "date": "2025-01-14",
        "price": 441.22
      },
      {
        "date": "2025-01-15",
        "price": 446.78
      },
      {
        "date": "2025-01-16",
        "price": 454.28
      },
      {
        "date": "2025-01-17",
        "price": 452.39
      },
      {
        "date": "2025-01-21",
        "price": 465.18
      },
      {
        "date": "2025-01-22",
        "price": 465.11
      },
      {
        "date": "2025-01-23",
        "price": 421.64
      },
      {
        "date": "2025-01-24",
        "price": 406.42
      },
      {
        "date": "2025-01-27",
        "price": 420.81
      },
      {
        "date": "2025-01-28",
        "price": 392.1
      },
      {
        "date": "2025-01-29",
        "price": 385.71
      },
      {
        "date": "2025-01-30",
        "price": 386.68
      },
      {
        "date": "2025-01-31",
        "price": 386.26
      },
      {
        "date": "2025-02-03",
        "price": 384.73
      },
      {
        "date": "2025-02-04",
        "price": 386.36
      },
      {
        "date": "2025-02-05",
        "price": 380.12
      },
      {
        "date": "2025-02-06",
        "price": 375.25
      },
      {
        "date": "2025-02-07",
        "price": 376.18
      },
      {
        "date": "2025-02-10",
        "price": 382.1
      },
      {
        "date": "2025-02-11",
        "price": 364.92
      },
      {
        "date": "2025-02-12",
        "price": 355.75
      },
      {
        "date": "2025-02-13",
        "price": 343.01
      },
      {
        "date": "2025-02-14",
        "price": 338.51
      },
      {
        "date": "2025-02-18",
        "price": 339.14
      },
      {
        "date": "2025-02-19",
        "price": 344.51
      },
      {
        "date": "2025-02-20",
        "price": 341.68
      },
      {
        "date": "2025-02-21",
        "price": 327.0
      },
      {
        "date": "2025-02-24",
        "price": 327.17
      },
      {
        "date": "2025-02-25",
        "price": 332.26
      },
      {
        "date": "2025-02-26",
        "price": 331.06
      },
      {
        "date": "2025-02-27",
        "price": 335.63
      },
      {
        "date": "2025-02-28",
        "price": 334.85
      },
      {
        "date": "2025-03-03",
        "price": 329.54
      },
      {
        "date": "2025-03-04",
        "price": 353.02
      },
      {
        "date": "2025-03-05",
        "price": 362.87
      },
      {
        "date": "2025-03-06",
        "price": 358.96
      },
      {
        "date": "2025-03-07",
        "price": 387.17
      },
      {
        "date": "2025-03-10",
        "price": 378.77
      },
      {
        "date": "2025-03-11",
        "price": 366.94
      },
      {
        "date": "2025-03-12",
        "price": 370.02
      },
      {
        "date": "2025-03-13",
        "price": 367.59
      },
      {
        "date": "2025-03-14",
        "price": 373.33
      },
      {
        "date": "2025-03-17",
        "price": 387.83
      },
      {
        "date": "2025-03-18",
        "price": 390.0
      },
      {
        "date": "2025-03-19",
        "price": 386.89
      },
      {
        "date": "2025-03-20",
        "price": 369.66
      },
      {
        "date": "2025-03-21",
        "price": 366.12
      },
      {
        "date": "2025-03-24",
        "price": 371.48
      },
      {
        "date": "2025-03-25",
        "price": 372.7
      },
      {
        "date": "2025-03-26",
        "price": 372.97
      },
      {
        "date": "2025-03-27",
        "price": 375.99
      },
      {
        "date": "2025-03-28",
        "price": 373.37
      },
      {
        "date": "2025-03-31",
        "price": 366.92
      },
      {
        "date": "2025-04-01",
        "price": 369.9
      },
      {
        "date": "2025-04-02",
        "price": 391.26
      },
      {
        "date": "2025-04-03",
        "price": 392.06
      },
      {
        "date": "2025-04-04",
        "price": 386.11
      },
      {
        "date": "2025-04-07",
        "price": 387.22
      },
      {
        "date": "2025-04-08",
        "price": 386.7
      },
      {
        "date": "2025-04-09",
        "price": 404.0
      },
      {
        "date": "2025-04-10",
        "price": 403.42
      },
      {
        "date": "2025-04-11",
        "price": 412.69
      },
      {
        "date": "2025-04-14",
        "price": 424.05
      },
      {
        "date": "2025-04-15",
        "price": 417.22
      },
      {
        "date": "2025-04-16",
        "price": 414.93
      },
      {
        "date": "2025-04-17",
        "price": 420.0
      },
      {
        "date": "2025-04-21",
        "price": 418.77
      },
      {
        "date": "2025-04-22",
        "price": 422.71
      },
      {
        "date": "2025-04-23",
        "price": 423.37
      },
      {
        "date": "2025-04-24",
        "price": 456.67
      },
      {
        "date": "2025-04-25",
        "price": 449.49
      },
      {
        "date": "2025-04-28",
        "price": 448.82
      },
      {
        "date": "2025-04-29",
        "price": 449.15
      },
      {
        "date": "2025-04-30",
        "price": 457.87
      },
      {
        "date": "2025-05-01",
        "price": 458.87
      },
      {
        "date": "2025-05-02",
        "price": 463.17
      },
      {
        "date": "2025-05-05",
        "price": 461.6
      },
      {
        "date": "2025-05-06",
        "price": 471.52
      },
      {
        "date": "2025-05-07",
        "price": 474.16
      },
      {
        "date": "2025-05-08",
        "price": 476.27
      },
      {
        "date": "2025-05-09",
        "price": 477.82
      },
      {
        "date": "2025-05-12",
        "price": 475.79
      },
      {
        "date": "2025-05-13",
        "price": 462.04
      },
      {
        "date": "2025-05-14",
        "price": 466.69
      },
      {
        "date": "2025-05-15",
        "price": 476.98
      },
      {
        "date": "2025-05-16",
        "price": 479.15
      },
      {
        "date": "2025-05-19",
        "price": 477.92
      },
      {
        "date": "2025-05-20",
        "price": 477.29
      },
      {
        "date": "2025-05-21",
        "price": 472.63
      },
      {
        "date": "2025-05-22",
        "price": 474.75
      },
      {
        "date": "2025-05-23",
        "price": 461.62
      },
      {
        "date": "2025-05-27",
        "price": 467.27
      },
      {
        "date": "2025-05-28",
        "price": 446.72
      },
      {
        "date": "2025-05-29",
        "price": 429.18
      },
      {
        "date": "2025-05-30",
        "price": 428.0
      },
      {
        "date": "2025-06-02",
        "price": 415.93
      }
    ],
    "current_price_data": {
      "price": 415.93,
      "change": -11.81,
      "percent_change": -2.76
    }
  },
  "news_sentiment": {
    "summary": "Synth\u00e8se courte :\n\nCACI International (CACI) a r\u00e9ussi \u00e0 franchir le seuil de 7,7 milliards de dollars de revenus pour entrer dans la liste des entreprises les plus grandes d'Am\u00e9rique du Nord, la Fortune 500. L'entreprise a \u00e9galement r\u00e9alis\u00e9 un placement d'un milliard de dollars de pr\u00eats s\u00e9niors. Le stock de CACI est consid\u00e9r\u00e9 comme un stock fort de valeur, en raison de ses profits \u00e9lev\u00e9s, de sa croissance continue et de sa position strat\u00e9gique dans le march\u00e9 de la d\u00e9fense. CACI a \u00e9galement obtenu des contrats d'intelligence \u00e0 un montant",
    "sentiment_score": 0.3,
    "label": "POSITIVE",
    "positive_ratio": 0.3,
    "neutral_ratio": 0.7,
    "negative_ratio": 0.0,
    "bullet_positive_count": 1,
    "bullet_negative_count": 1,
    "headlines": []
  },
  "extraction_date": "2025-06-02"
}