{
  "ticker": "CAH",
  "name": "Cardinal Health",
  "sector": "Health Care",
  "market_cap": 36815925248.0,
  "source_list": "SP500",
  "fundamentals": {
    "PE": 24.101562,
    "PB": -12.505067,
    "EV_Revenue": 0.19,
    "ROE": 0.151085,
    "ProfitMargin": 0.0069999998,
    "GrossMargin": 0.03531,
    "DividendYield": 1.33
  },
  "technical_indicators": {
    "RSI_14": 71.47739619906699,
    "Momentum_10": 3.156558054728367,
    "MACD": 4.729656181656935,
    "BB_Percent": 0.8385305575618762,
    "SMA20_above_SMA50": 1.0
  },
  "scores": {
    "ValueScore": 0.907271906726187,
    "QualityScore": 0.3202538868087237,
    "SignalScore": 0.5650608758512885
  },
  "volatility": 0.0141383054421898,
  "beta": 0.674,
  "return_6m": 0.2953747845538303,
  "analyst_rating": {
    "recommendation": "buy",
    "analyst_count": 15,
    "target_mean_price": 156.74133
  },
  "visual_data": {
    "sparkline": [
      {
        "date": "2024-12-02",
        "price": 122.47
      },
      {
        "date": "2024-12-03",
        "price": 123.27
      },
      {
        "date": "2024-12-04",
        "price": 125.24
      },
      {
        "date": "2024-12-05",
        "price": 122.84
      },
      {
        "date": "2024-12-06",
        "price": 122.76
      },
      {
        "date": "2024-12-09",
        "price": 121.58
      },
      {
        "date": "2024-12-10",
        "price": 120.42
      },
      {
        "date": "2024-12-11",
        "price": 117.42
      },
      {
        "date": "2024-12-12",
        "price": 117.46
      },
      {
        "date": "2024-12-13",
        "price": 118.1
      },
      {
        "date": "2024-12-16",
        "price": 116.55
      },
      {
        "date": "2024-12-17",
        "price": 115.82
      },
      {
        "date": "2024-12-18",
        "price": 115.91
      },
      {
        "date": "2024-12-19",
        "price": 117.0
      },
      {
        "date": "2024-12-20",
        "price": 118.28
      },
      {
        "date": "2024-12-23",
        "price": 118.35
      },
      {
        "date": "2024-12-24",
        "price": 118.83
      },
      {
        "date": "2024-12-26",
        "price": 119.2
      },
      {
        "date": "2024-12-27",
        "price": 119.14
      },
      {
        "date": "2024-12-30",
        "price": 117.92
      },
      {
        "date": "2024-12-31",
        "price": 118.27
      },
      {
        "date": "2025-01-02",
        "price": 118.02
      },
      {
        "date": "2025-01-03",
        "price": 119.3
      },
      {
        "date": "2025-01-06",
        "price": 119.63
      },
      {
        "date": "2025-01-07",
        "price": 121.4
      },
      {
        "date": "2025-01-08",
        "price": 122.53
      },
      {
        "date": "2025-01-10",
        "price": 121.57
      },
      {
        "date": "2025-01-13",
        "price": 120.86
      },
      {
        "date": "2025-01-14",
        "price": 124.03
      },
      {
        "date": "2025-01-15",
        "price": 124.71
      },
      {
        "date": "2025-01-16",
        "price": 127.03
      },
      {
        "date": "2025-01-17",
        "price": 126.27
      },
      {
        "date": "2025-01-21",
        "price": 127.83
      },
      {
        "date": "2025-01-22",
        "price": 128.75
      },
      {
        "date": "2025-01-23",
        "price": 129.3
      },
      {
        "date": "2025-01-24",
        "price": 128.83
      },
      {
        "date": "2025-01-27",
        "price": 130.73
      },
      {
        "date": "2025-01-28",
        "price": 127.73
      },
      {
        "date": "2025-01-29",
        "price": 127.76
      },
      {
        "date": "2025-01-30",
        "price": 128.26
      },
      {
        "date": "2025-01-31",
        "price": 123.66
      },
      {
        "date": "2025-02-03",
        "price": 125.33
      },
      {
        "date": "2025-02-04",
        "price": 125.17
      },
      {
        "date": "2025-02-05",
        "price": 127.45
      },
      {
        "date": "2025-02-06",
        "price": 127.05
      },
      {
        "date": "2025-02-07",
        "price": 127.37
      },
      {
        "date": "2025-02-10",
        "price": 127.2
      },
      {
        "date": "2025-02-11",
        "price": 128.39
      },
      {
        "date": "2025-02-12",
        "price": 127.06
      },
      {
        "date": "2025-02-13",
        "price": 126.78
      },
      {
        "date": "2025-02-14",
        "price": 126.21
      },
      {
        "date": "2025-02-18",
        "price": 126.25
      },
      {
        "date": "2025-02-19",
        "price": 126.75
      },
      {
        "date": "2025-02-20",
        "price": 127.38
      },
      {
        "date": "2025-02-21",
        "price": 127.06
      },
      {
        "date": "2025-02-24",
        "price": 127.55
      },
      {
        "date": "2025-02-25",
        "price": 127.81
      },
      {
        "date": "2025-02-26",
        "price": 127.18
      },
      {
        "date": "2025-02-27",
        "price": 127.47
      },
      {
        "date": "2025-02-28",
        "price": 129.48
      },
      {
        "date": "2025-03-03",
        "price": 129.18
      },
      {
        "date": "2025-03-04",
        "price": 126.31
      },
      {
        "date": "2025-03-05",
        "price": 127.42
      },
      {
        "date": "2025-03-06",
        "price": 127.01
      },
      {
        "date": "2025-03-07",
        "price": 126.5
      },
      {
        "date": "2025-03-10",
        "price": 123.93
      },
      {
        "date": "2025-03-11",
        "price": 124.17
      },
      {
        "date": "2025-03-12",
        "price": 126.83
      },
      {
        "date": "2025-03-13",
        "price": 126.27
      },
      {
        "date": "2025-03-14",
        "price": 128.0
      },
      {
        "date": "2025-03-17",
        "price": 130.03
      },
      {
        "date": "2025-03-18",
        "price": 131.46
      },
      {
        "date": "2025-03-19",
        "price": 132.12
      },
      {
        "date": "2025-03-20",
        "price": 133.08
      },
      {
        "date": "2025-03-21",
        "price": 131.89
      },
      {
        "date": "2025-03-24",
        "price": 133.21
      },
      {
        "date": "2025-03-25",
        "price": 132.75
      },
      {
        "date": "2025-03-26",
        "price": 133.98
      },
      {
        "date": "2025-03-27",
        "price": 136.65
      },
      {
        "date": "2025-03-28",
        "price": 136.44
      },
      {
        "date": "2025-03-31",
        "price": 137.77
      },
      {
        "date": "2025-04-01",
        "price": 137.13
      },
      {
        "date": "2025-04-02",
        "price": 138.67
      },
      {
        "date": "2025-04-03",
        "price": 137.09
      },
      {
        "date": "2025-04-04",
        "price": 129.63
      },
      {
        "date": "2025-04-07",
        "price": 125.68
      },
      {
        "date": "2025-04-08",
        "price": 125.0
      },
      {
        "date": "2025-04-09",
        "price": 130.45
      },
      {
        "date": "2025-04-10",
        "price": 128.88
      },
      {
        "date": "2025-04-11",
        "price": 131.77
      },
      {
        "date": "2025-04-14",
        "price": 134.78
      },
      {
        "date": "2025-04-15",
        "price": 134.25
      },
      {
        "date": "2025-04-16",
        "price": 134.36
      },
      {
        "date": "2025-04-17",
        "price": 134.71
      },
      {
        "date": "2025-04-21",
        "price": 131.17
      },
      {
        "date": "2025-04-22",
        "price": 133.69
      },
      {
        "date": "2025-04-23",
        "price": 134.43
      },
      {
        "date": "2025-04-24",
        "price": 135.84
      },
      {
        "date": "2025-04-25",
        "price": 137.56
      },
      {
        "date": "2025-04-28",
        "price": 138.24
      },
      {
        "date": "2025-04-29",
        "price": 139.84
      },
      {
        "date": "2025-04-30",
        "price": 141.29
      },
      {
        "date": "2025-05-01",
        "price": 145.53
      },
      {
        "date": "2025-05-02",
        "price": 149.53
      },
      {
        "date": "2025-05-05",
        "price": 151.99
      },
      {
        "date": "2025-05-06",
        "price": 151.69
      },
      {
        "date": "2025-05-07",
        "price": 153.48
      },
      {
        "date": "2025-05-08",
        "price": 147.27
      },
      {
        "date": "2025-05-09",
        "price": 148.22
      },
      {
        "date": "2025-05-12",
        "price": 148.62
      },
      {
        "date": "2025-05-13",
        "price": 148.26
      },
      {
        "date": "2025-05-14",
        "price": 148.41
      },
      {
        "date": "2025-05-15",
        "price": 151.95
      },
      {
        "date": "2025-05-16",
        "price": 154.25
      },
      {
        "date": "2025-05-19",
        "price": 153.86
      },
      {
        "date": "2025-05-20",
        "price": 154.77
      },
      {
        "date": "2025-05-21",
        "price": 153.31
      },
      {
        "date": "2025-05-22",
        "price": 152.49
      },
      {
        "date": "2025-05-23",
        "price": 152.75
      },
      {
        "date": "2025-05-27",
        "price": 154.68
      },
      {
        "date": "2025-05-28",
        "price": 153.13
      },
      {
        "date": "2025-05-29",
        "price": 153.99
      },
      {
        "date": "2025-05-30",
        "price": 154.44
      }
    ],
    "current_price_data": {
      "price": 154.44,
      "change": 0.45,
      "percent_change": 0.29
    }
  },
  "news_sentiment": {
    "summary": "Cardinal Health (CAH) has been a favorite among institutional investors, with them owning 89% of the company. The healthcare stock is seen as a top value stock for the long-term by Yahoo Finance, and is also recommended by MSN. Value investors are considering buying CAH stock, according to Nasdaq. Despite market gains, CAH stock has dropped slightly, and its performance is being compared to other drug distribution giants such as McKesson (MCK). CAH has announced a new quarterly dividend and has been performing well this year, with its stock up nearly 7%. However, there are concerns about the sustainability of demand for CAH's products before the Q3 earnings. Overall, the sentiment towards CAH stock is",
    "sentiment_score": -0.15,
    "label": "POSITIVE",
    "positive_ratio": 0.1,
    "neutral_ratio": 0.65,
    "negative_ratio": 0.25,
    "bullet_positive_count": 0,
    "bullet_negative_count": 0,
    "headlines": [
      {
        "title": "Why Cardinal Health (CAH) is a Top Value Stock for the Long-Term - Yahoo Finance",
        "url": "https://news.google.com/rss/articles/CBMifkFVX3lxTE9rSTJMdWVlbFFEZEpvdmV5NUQweXBrdFFHb28wbkx6LTVZNTVIUGhMZ3B4R2Y1TmV0US1JUkp2NkE5MXBIZ1JKZElXaS0xczJxRm9nVGcxaWl5WmxQWC1EU0EyZ3F5cC1tT2o4azNGUG10QlR2cXdLQlhaeE1xUQ?oc=5",
        "label": "NEUTRAL"
      },
      {
        "title": "Forget UnitedHealth. Cardinal Health Is the Best Healthcare Stock to Buy Right Now - MSN",
        "url": "https://news.google.com/rss/articles/CBMizgFBVV95cUxQVkV0LV94RzFScldZN1dRV3I2RUN2OVRwek84bHFNRHFCeUV1NHVQRW9IN0RiSlBqTmFhZUw5SGUzTFVRMkhuNE5LcjhtMi1xSWd4Q3FHNnhwNzBOTW96Nll2TVFNTU9zcmZTc2hPb2M5Tm9CVUlKaVdXWnVIUjZsb3A3YkRINUZHTDdXQTlvQTRnYzVwTm10bmhqVWZHa01XdWF5RExIX0FXbFlJaVBpdF9ZUVItUzJXQllYMUpmRTVMdEdzYlZUWFRaZ0Zkdw?oc=5",
        "label": "NEUTRAL"
      },
      {
        "title": "(CAH) Investment Report - news.stocktradersdaily.com",
        "url": "https://news.google.com/rss/articles/CBMinAFBVV95cUxNbUE4Wkx1QWYza2QwN3kwWVE5UTJUcjZIQ3lqTE1JZEt2bjhPYzkzWl9kYkl1VUVSNXZUUmRqbkt5QWFaVGxUOHhCMUNrNU82ZHk3UFpyamk1bUlNUmc2VzRhbTlVOUt4WFZOTW5meGI1eGRtbldaYzJST3laUWpyc3NvMXZpbThWWTJxOHlhTEpPNEtUb21KRjQycWk?oc=5",
        "label": "NEUTRAL"
      },
      {
        "title": "Cardinal Health, Inc. (NYSE:CAH) is a favorite amongst institutional investors who own 89% - simplywall.st",
        "url": "https://news.google.com/rss/articles/CBMizgFBVV95cUxQV0p5dWlHT2dfZldjZmZBREtld00yZVJJTExMMXNQd2hCV3lJeVNRV2lPeXJKVFRwVFI0bFZWMk5MaFRBTWJBWGUxenFXUGxta3VOVmdiekRMaUlEdk1hRVdfUkxlTm5VNFpzbXVaM3NEenA1Mk5aV1dadjZHc2dGRGZ5a0pJUlN1MHVGa2VidGstT2M4aE5SbWx1Znp5YlNNY1h6YWk1VG0wVUhZMkg5SGdscjVBY3RSeWFTaWpyNlBOQlJNUVc4TC1zTkw5Z9IB0wFBVV95cUxOLS15MndsVmRZN3Qwc1FoQWJnNHJtTjRzbFFKRDVNelUyMS1UVG94bjZLc0FaOVY5bTJPTFZVY0ZLaFM4UnhFemVaOHAyM2tObFZWWDJmN0pZNjBSOElseEoxZVRrVTlPOGFXWlVLRkc1M1FPNm0yNHRUMkxBUGdBajhhTTVNU0k0QUpDLXJTOTVqU1oxdFdCRmdGT0RJM2RJaVZVd2dDekhEUWIyUjFHN2Y4Qi1jTE5uLVF2a3lCdC1QSUg0V2lWZTB0LS16SnA3TnlF?oc=5",
        "label": "NEUTRAL"
      },
      {
        "title": "Should Value Investors Buy Cardinal Health (CAH) Stock? - Nasdaq",
        "url": "https://news.google.com/rss/articles/CBMikAFBVV95cUxQYmI0WmRjcXJ2MThxZVFpWkpLVDg5UUJLM2NOOVlXYXNaUXNrTTgyU3hfWFZpZHE5a2VFdFVibHRhbDVwak9uWmdSUmJ4Y2hzTm5ZZ0lyY25FNHRaR19NQXQyMVlqaUF0dmNTUXpmSXczSXM0VlgzYkJUQ3pPWlBUTTVybXlOTDFMTEF4Uk1WZlc?oc=5",
        "label": "NEUTRAL"
      },
      {
        "title": "Doubt the Market? 3 Stocks to Rideout Fear, Uncertainty and Doubt - MarketBeat",
        "url": "https://news.google.com/rss/articles/CBMipgFBVV95cUxPMldUblVCYm9qV0xPWTRqYzVvZDFjWEhNeWlYdjQwUHRaNjBlc3N0RXFRMEJzRnk1eFpqUXRpaDdtSXpTNE1CRHpXTXpvaHlDNzhMdDR0VURnNFJaUU82UmQ4bGMyYktMM2gwNEJFMzZLcEFCVFJocFBSanFyd0p5RTZkajl3aHNEQUdtMDRQRVU2Ri0yZ0N4ZW9sc1pXa0xtdnFhbmdB?oc=5",
        "label": "NEUTRAL"
      },
      {
        "title": "MCK vs. CAH: Which Drug Distribution Giant Has the Healthier Outlook? - The Globe and Mail",
        "url": "https://news.google.com/rss/articles/CBMi5gFBVV95cUxPMzVPVXg2YzVWYS1IODZoN043OUFTTk9qVGIyTUEzVG1GZWpDVVQwR2VldXZaMFpiS2V4RVd4OWtRUFAtanVaRWxuVy1FbmNteWFVQk1BOUgtdEkzZ2pud3Nmb0NCemhacElUeWRlV0ZiTmh3eDRvcmRySlVHcDRkUURyaGdjdG9nakEzek5SaDhLRUlTMEJYRVEwbkpiWkJkYzJvcTY4cWg4WUJDUnA5Mkw1YVVrUTAtLVo3S005ZzJ3SEhJVGotbHVWY1k4RlAzYmFfeFJJWjRubU40Qm9FdFpxUmltQQ?oc=5",
        "label": "NEUTRAL"
      },
      {
        "title": "Cardinal Health Boosts Shareholder Returns: New $0.5107 Quarterly Dividend Announced - Stock Titan",
        "url": "https://news.google.com/rss/articles/CBMiqwFBVV95cUxORU1pa2wyNDF2Uk5aMXN4NjJ4cmNSNG5IamJRY3ByZ1gzLTRWVmVFQ0V0MF9jSmlfT3RyX0ZHVlJMOE5EbV81TnBYdlRkUjhYaDRNNXhQTDVGQlNpUkFFZGNibm9wd0ZqMUdSQ3RWd2JHOVJ6bTBWejktd25FSWFPTjZGQmZ1Qi1hcGU2T1VWRlk4ODd4RUs3N0Z5alQ2UjZqNHZ5QjdZZnF6SUk?oc=5",
        "label": "POSITIVE"
      },
      {
        "title": "Cardinal Health (CAH) Stock Moves -1.14%: What You Should Know - Yahoo Finance",
        "url": "https://news.google.com/rss/articles/CBMigwFBVV95cUxNWjNtUE0zbkEya1pqS2stb1FuQUNWUEJzWktXRFd2Yzh3bUQ5SC1Ob1libWthOExqWWtzcEtsamR4ekpydlB2ZVh1dVR4ck5BZFd0SGRELVAySFkwcFM0SlBSdXJOdk5INThOeWRkdXgzMm9rUzA1Vmh5SXRGdE1rRGNRZw?oc=5",
        "label": "NEUTRAL"
      },
      {
        "title": "Cardinal Health Stock: Is CAH Outperforming the Healthcare Sector? - Nasdaq",
        "url": "https://news.google.com/rss/articles/CBMikwFBVV95cUxNNzc1LWVlVDJvdUVzNzJ0ejV5aWpxdzhfUkdiTHR6YXJoUkQyYUlEcU9zQVhCcnMyRC1QYTlmX20yYWxsTVBHQzJFMlRfU00tQnJqT0R4blhfWFJUQjE2RXFKWWdPZVAtc21hblZYQm1xZTcwdVF6cUZ5d21nM2JrY29PUjExYzdZeVlnb0IwZnVvUXM?oc=5",
        "label": "NEGATIVE"
      },
      {
        "title": "Cardinal Health (CAH) Stock Drops Despite Market Gains: Important Facts to Note - Yahoo Finance",
        "url": "https://news.google.com/rss/articles/CBMigwFBVV95cUxObVVUZXl3RXFBblRLMC1halFHR0t2dDFJNHRxSndSclBISjFtMUlKTWJiZUlkQ2dFQ0NvcnFteDJIZzBVTTdwTEdSR2MybXVkeFYxVUxzU0NJWWxUN0RFLUtVUmhxdWVCNDdLaTJzQ1ZWYnd4eVVzZ0NTWk94MmxDQzh6OA?oc=5",
        "label": "NEGATIVE"
      },
      {
        "title": "Can Sustained Product Demand Drive CAH Stock Before Q3 Earnings? - Nasdaq",
        "url": "https://news.google.com/rss/articles/CBMikgFBVV95cUxOZTVJSDcwT3piMDk5MDNOYkxRSE5SM280MnAwczRVaGIwWElIS0lHY2MwZ09fZXc0czRLUkh0STVrbkZkbVkyZHpHaEwycDg1VlVPa0UzN1FsdnVkU2FYU1VjcE1HcGNORUhxa0FfMWxKc2l4bU5McWVkdTlzcFliWGp6aEtDNks1MEJ2NTFfVS1WQQ?oc=5",
        "label": "NEUTRAL"
      },
      {
        "title": "CAH Stock Up Nearly 7% This Year: Is Now the Time to Buy? - Yahoo Finance",
        "url": "https://news.google.com/rss/articles/CBMid0FVX3lxTFA3NEF5c1kzMXVrZEdjMTBabU5FZlBtUDZGci04QU9CQW5GbHl4QXU5Wjk5dGhrdDVXY1k2SXdTQU1iUFVfTkF4VTRKSU81WEs1c1VPd3NtOXpkOEgwSFRlODI3cWxkdlNpZmVZR0I2SnhlTEozaHRJ?oc=5",
        "label": "POSITIVE"
      },
      {
        "title": "Are Medical Stocks Lagging Cardinal Health (CAH) This Year? - Yahoo Finance",
        "url": "https://news.google.com/rss/articles/CBMijAFBVV95cUxNamRSMWNrQ3FfTFd3Mm5JUmVTM3FBZDRRRWNBRTAzZ09iSVFfRDhKTjM5UW5WZWd0d0pKb3lXTkZfRjhrTGlPMkFvZUxRcm5uSEg1RnA5Wm5nMlhEYlEyMHFuNlM4SDNLZjBMWHVSUko1MXRLQkoyMzd1S2g5aXFTOHdpWlNVMjIyR1QyaQ?oc=5",
        "label": "NEGATIVE"
      },
      {
        "title": "Here's Why Cardinal Health (CAH) is a Strong Value Stock - Yahoo Finance",
        "url": "https://news.google.com/rss/articles/CBMigAFBVV95cUxOUFphaE9wc016OGhYSWVZM09TMGJiMW1mcldhclJMSHNUYzlQR0tpX3phN2Jxd3ZFSXVOQW1OQ1RUM0FORE1SSFhHNHRzcEpBUzhzUUs1el9HTHp0MW05MGxXNU5KdWhHUWM0M0N1UG5JNS1MdVQzSmxlemhzbllFdw?oc=5",
        "label": "NEUTRAL"
      },
      {
        "title": "CAH Stock Rises More Than 13% YTD: Should You Buy, Hold or Sell? - Yahoo Finance",
        "url": "https://news.google.com/rss/articles/CBMieEFVX3lxTE52dGp0V3pmemRIVndNQjI5RExPQXh0Vm5hV1doREFRdzJzOFNBcDBCMEk3eEJQbTNjM2xNZmp5NnZ2YkpMaXJaVHVGeC1NRk11b2JtRTBBWjVKbUw0RFJ0X3VBSnVRVlQ5X3FJTjdrQ3hiZXF0UGh3WQ?oc=5",
        "label": "NEUTRAL"
      },
      {
        "title": "Healthcare Providers & Services Stocks Q4 Teardown: Cardinal Health (NYSE:CAH) Vs The Rest - Yahoo Finance",
        "url": "https://news.google.com/rss/articles/CBMijgFBVV95cUxPaU1NeFEtdHJkejF4a0pLZ0hodjdzek5mME9hUlRueHJRM0gtWmo5SVB0Mkd0dDF1RkFKVThXczhNMzFwRHBRWEZtZHZJWU1Vc1lzS2FOWmY4c2NaODBPd1NobmwyUHlQb1hWRk5IbzFhYWQzNkF3UnJLLV9uZEM3V2czbUFtZnVreHdzZVln?oc=5",
        "label": "NEGATIVE"
      },
      {
        "title": "Cardinal Health (NYSE:CAH) Misses Q1 Revenue Estimates - Yahoo Finance",
        "url": "https://news.google.com/rss/articles/CBMigwFBVV95cUxQdFNOUy1YWVR4eFJhU2xPYkw0dENiQkdRWWVqZmdoZnlkTXRyNVZnUGtFMERDaXJMVmVDVmFYT1lFNjlKM2hvTzJlSmNhUXA2cEt1Q3dEWFpXS3UxX0JzY3NnX0tUX1NMTng4dUxHMGYxdDV3VlMtODhJN0ZGV0p0SFQ3bw?oc=5",
        "label": "NEUTRAL"
      },
      {
        "title": "Are Wall Street Analysts Predicting Cardinal Health Stock Will Climb or Sink? - Nasdaq",
        "url": "https://news.google.com/rss/articles/CBMirAFBVV95cUxOMlVhMG9sbWlMNWx3SGliSUlLZGV0ZkdBMjRtemQxdXBRNVpRTzgzQm0wd3NBckw5Ynl0QlVDdV9NNUY5ajdrZHY3OV9rOTNxVWZRczN4UmhneVVZWUFmT01zS3FKMVZJZEtudVNrR09yWHg2eldrLTBLRU1TWGFGQk0zck4tOFJ6Nk9pLTlBektETTc3V0JfNjBzWlJEaVZqVGY4cjk4STBfWTFa?oc=5",
        "label": "NEGATIVE"
      },
      {
        "title": "Cardinal Health Board of Directors Approves Quarterly Dividend - PR Newswire",
        "url": "https://news.google.com/rss/articles/CBMiugFBVV95cUxQYXBya2w4OFJkd0locjFNNjhCcm0tRVZXa0lSQjJBbzlxclZOSE1TMTdkYXJtWFdwbGpwNjVrMXZ5UzVWbnVZYzJYbUhfUF8xaUZaMVp0anN6dGdmTEE4WmgyMmdkeUxGc3lXT0Z2ZlJSVlRWakoxM2h3Tl9tSDlWMlBDRV84VF83R1p5T0JYSUJlRXdSYXRveDZXVjNEaTlaeWlOWHlWdlpQZ2V4bVlncVpRdWFhZDNyRWc?oc=5",
        "label": "NEUTRAL"
      }
    ]
  },
  "extraction_date": "2025-05-16"
}