{
  "ticker": "HOLX",
  "name": "Hologic",
  "sector": "Health Care",
  "market_cap": 12655367168.0,
  "source_list": "SP500",
  "fundamentals": {
    "PE": 23.861343,
    "PB": 2.7400367,
    "EV_Revenue": 3.368,
    "ROE": 0.11766,
    "ProfitMargin": 0.13826,
    "GrossMargin": 0.61013,
    "DividendYield": null
  },
  "technical_indicators": {
    "RSI_14": 48.01194983178509,
    "Momentum_10": 4.855984260570307,
    "MACD": -0.8332168977453662,
    "BB_Percent": 0.5151982813779744,
    "SMA20_above_SMA50": 0.0
  },
  "scores": {
    "ValueScore": 0.8907830499288327,
    "QualityScore": 0.4434868222258413,
    "SignalScore": 0.67372525090053
  },
  "volatility": 0.0180480211437353,
  "beta": 0.546,
  "return_6m": -0.2792232484371555,
  "analyst_rating": {
    "recommendation": "buy",
    "analyst_count": 15,
    "target_mean_price": 67.14133
  },
  "visual_data": {
    "sparkline": [
      {
        "date": "2024-12-02",
        "price": 79.0
      },
      {
        "date": "2024-12-03",
        "price": 77.47
      },
      {
        "date": "2024-12-04",
        "price": 76.87
      },
      {
        "date": "2024-12-05",
        "price": 76.0
      },
      {
        "date": "2024-12-06",
        "price": 75.34
      },
      {
        "date": "2024-12-09",
        "price": 75.79
      },
      {
        "date": "2024-12-10",
        "price": 76.83
      },
      {
        "date": "2024-12-11",
        "price": 75.53
      },
      {
        "date": "2024-12-12",
        "price": 75.09
      },
      {
        "date": "2024-12-13",
        "price": 73.65
      },
      {
        "date": "2024-12-16",
        "price": 72.44
      },
      {
        "date": "2024-12-17",
        "price": 72.26
      },
      {
        "date": "2024-12-18",
        "price": 71.47
      },
      {
        "date": "2024-12-19",
        "price": 70.76
      },
      {
        "date": "2024-12-20",
        "price": 71.65
      },
      {
        "date": "2024-12-23",
        "price": 72.5
      },
      {
        "date": "2024-12-24",
        "price": 72.68
      },
      {
        "date": "2024-12-26",
        "price": 72.72
      },
      {
        "date": "2024-12-27",
        "price": 72.6
      },
      {
        "date": "2024-12-30",
        "price": 72.27
      },
      {
        "date": "2024-12-31",
        "price": 72.09
      },
      {
        "date": "2025-01-02",
        "price": 71.74
      },
      {
        "date": "2025-01-03",
        "price": 73.19
      },
      {
        "date": "2025-01-06",
        "price": 73.77
      },
      {
        "date": "2025-01-07",
        "price": 72.69
      },
      {
        "date": "2025-01-08",
        "price": 72.74
      },
      {
        "date": "2025-01-10",
        "price": 71.7
      },
      {
        "date": "2025-01-13",
        "price": 70.29
      },
      {
        "date": "2025-01-14",
        "price": 70.2
      },
      {
        "date": "2025-01-15",
        "price": 68.75
      },
      {
        "date": "2025-01-16",
        "price": 69.97
      },
      {
        "date": "2025-01-17",
        "price": 69.73
      },
      {
        "date": "2025-01-21",
        "price": 70.37
      },
      {
        "date": "2025-01-22",
        "price": 71.19
      },
      {
        "date": "2025-01-23",
        "price": 70.7
      },
      {
        "date": "2025-01-24",
        "price": 71.02
      },
      {
        "date": "2025-01-27",
        "price": 72.75
      },
      {
        "date": "2025-01-28",
        "price": 71.77
      },
      {
        "date": "2025-01-29",
        "price": 71.41
      },
      {
        "date": "2025-01-30",
        "price": 72.17
      },
      {
        "date": "2025-01-31",
        "price": 72.14
      },
      {
        "date": "2025-02-03",
        "price": 71.72
      },
      {
        "date": "2025-02-04",
        "price": 71.58
      },
      {
        "date": "2025-02-05",
        "price": 72.8
      },
      {
        "date": "2025-02-06",
        "price": 65.45
      },
      {
        "date": "2025-02-07",
        "price": 64.58
      },
      {
        "date": "2025-02-10",
        "price": 65.24
      },
      {
        "date": "2025-02-11",
        "price": 64.47
      },
      {
        "date": "2025-02-12",
        "price": 63.53
      },
      {
        "date": "2025-02-13",
        "price": 63.62
      },
      {
        "date": "2025-02-14",
        "price": 63.24
      },
      {
        "date": "2025-02-18",
        "price": 63.93
      },
      {
        "date": "2025-02-19",
        "price": 64.2
      },
      {
        "date": "2025-02-20",
        "price": 64.32
      },
      {
        "date": "2025-02-21",
        "price": 64.49
      },
      {
        "date": "2025-02-24",
        "price": 65.01
      },
      {
        "date": "2025-02-25",
        "price": 65.23
      },
      {
        "date": "2025-02-26",
        "price": 64.36
      },
      {
        "date": "2025-02-27",
        "price": 63.21
      },
      {
        "date": "2025-02-28",
        "price": 63.39
      },
      {
        "date": "2025-03-03",
        "price": 63.27
      },
      {
        "date": "2025-03-04",
        "price": 62.3
      },
      {
        "date": "2025-03-05",
        "price": 62.08
      },
      {
        "date": "2025-03-06",
        "price": 62.5
      },
      {
        "date": "2025-03-07",
        "price": 64.54
      },
      {
        "date": "2025-03-10",
        "price": 65.62
      },
      {
        "date": "2025-03-11",
        "price": 62.59
      },
      {
        "date": "2025-03-12",
        "price": 61.1
      },
      {
        "date": "2025-03-13",
        "price": 60.7
      },
      {
        "date": "2025-03-14",
        "price": 60.71
      },
      {
        "date": "2025-03-17",
        "price": 61.82
      },
      {
        "date": "2025-03-18",
        "price": 61.98
      },
      {
        "date": "2025-03-19",
        "price": 61.47
      },
      {
        "date": "2025-03-20",
        "price": 61.01
      },
      {
        "date": "2025-03-21",
        "price": 61.47
      },
      {
        "date": "2025-03-24",
        "price": 61.89
      },
      {
        "date": "2025-03-25",
        "price": 60.8
      },
      {
        "date": "2025-03-26",
        "price": 61.48
      },
      {
        "date": "2025-03-27",
        "price": 62.32
      },
      {
        "date": "2025-03-28",
        "price": 61.32
      },
      {
        "date": "2025-03-31",
        "price": 61.77
      },
      {
        "date": "2025-04-01",
        "price": 61.38
      },
      {
        "date": "2025-04-02",
        "price": 60.56
      },
      {
        "date": "2025-04-03",
        "price": 61.69
      },
      {
        "date": "2025-04-04",
        "price": 60.86
      },
      {
        "date": "2025-04-07",
        "price": 61.27
      },
      {
        "date": "2025-04-08",
        "price": 58.46
      },
      {
        "date": "2025-04-09",
        "price": 59.31
      },
      {
        "date": "2025-04-10",
        "price": 57.16
      },
      {
        "date": "2025-04-11",
        "price": 57.85
      },
      {
        "date": "2025-04-14",
        "price": 58.84
      },
      {
        "date": "2025-04-15",
        "price": 57.86
      },
      {
        "date": "2025-04-16",
        "price": 56.5
      },
      {
        "date": "2025-04-17",
        "price": 57.56
      },
      {
        "date": "2025-04-21",
        "price": 56.94
      },
      {
        "date": "2025-04-22",
        "price": 58.19
      },
      {
        "date": "2025-04-23",
        "price": 58.15
      },
      {
        "date": "2025-04-24",
        "price": 58.29
      },
      {
        "date": "2025-04-25",
        "price": 58.02
      },
      {
        "date": "2025-04-28",
        "price": 58.08
      },
      {
        "date": "2025-04-29",
        "price": 58.36
      },
      {
        "date": "2025-04-30",
        "price": 58.2
      },
      {
        "date": "2025-05-01",
        "price": 57.28
      },
      {
        "date": "2025-05-02",
        "price": 54.16
      },
      {
        "date": "2025-05-05",
        "price": 52.73
      },
      {
        "date": "2025-05-06",
        "price": 53.11
      },
      {
        "date": "2025-05-07",
        "price": 55.43
      },
      {
        "date": "2025-05-08",
        "price": 56.18
      },
      {
        "date": "2025-05-09",
        "price": 56.75
      },
      {
        "date": "2025-05-12",
        "price": 58.81
      },
      {
        "date": "2025-05-13",
        "price": 57.12
      },
      {
        "date": "2025-05-14",
        "price": 55.36
      },
      {
        "date": "2025-05-15",
        "price": 55.74
      },
      {
        "date": "2025-05-16",
        "price": 56.79
      },
      {
        "date": "2025-05-19",
        "price": 56.43
      },
      {
        "date": "2025-05-20",
        "price": 56.47
      },
      {
        "date": "2025-05-21",
        "price": 54.82
      },
      {
        "date": "2025-05-22",
        "price": 54.48
      },
      {
        "date": "2025-05-23",
        "price": 54.28
      },
      {
        "date": "2025-05-27",
        "price": 62.17
      },
      {
        "date": "2025-05-28",
        "price": 63.71
      },
      {
        "date": "2025-05-29",
        "price": 62.92
      },
      {
        "date": "2025-05-30",
        "price": 62.17
      }
    ],
    "current_price_data": {
      "price": 62.17,
      "change": -0.75,
      "percent_change": -1.19
    }
  },
  "news_sentiment": {
    "summary": "Hologic (HOLX) stock has been surging recently due to a take-private offer and positive earnings reports. The company's shares have risen by 23% after trade resumption, and its Q1 earnings outperformed expectations. However, the company's three-year earnings and shareholder returns have been declining, and its stock has fallen 3.8% in the past week. The stock has been underperforming the healthcare sector in recent months, but Wall Street is bullish on the company's future prospects.",
    "sentiment_score": 0.15,
    "label": "NEUTRAL",
    "positive_ratio": 0.35,
    "neutral_ratio": 0.45,
    "negative_ratio": 0.2,
    "bullet_positive_count": 0,
    "bullet_negative_count": 0,
    "headlines": [
      {
        "title": "Why Is Hologic (HOLX) Stock Rocketing Higher Today - Yahoo Finance",
        "url": "https://news.google.com/rss/articles/CBMihAFBVV95cUxOSTNKcmNFUW5ZRGV4YVBrbER2QmxrVk1nZzVQWTBfMkNjS2RWVW9vS1IzMUNCRnNBb0hMd3RJQ2pTWElmVEpqT0lWRjhXMjJUZFdlSEVieXNVLXplajlScU1mUEZzZ2J2cHpCVUZfSVBwUEZEUTg1d09BcmNiZXIyY2NSSlc?oc=5",
        "label": "POSITIVE"
      },
      {
        "title": "Hologic (HOLX) Surges 23% After Trade Resumption | HOLX Stock Ne - GuruFocus",
        "url": "https://news.google.com/rss/articles/CBMiogFBVV95cUxPYUlNNHZrLXlpc3hUM0duOTB0aGJKbFd1RUNvd3RJb3lYWERqdmlyQnlKUFFHYkp2MnFmakloaHNiTEctcWpYN3BrdnMtZncwNGtUdmJKb2g3UlJHZUlZeHo4LXdKRW1OdE11eHZOa2tZdzY3MDlzOVpSM2dwcENJcjhpNlB6SmF0RG1ROWRSaDdHSXlTb2RfSUUxQWZfRFZXc0E?oc=5",
        "label": "POSITIVE"
      },
      {
        "title": "Hologic Stock Is Surging. Why Shares of the MedTech Company Are Up 14%. - Barron's",
        "url": "https://news.google.com/rss/articles/CBMiiwFBVV95cUxONjBERkhVR3E3ZzZla2FDZndkOVVqVUY2YzU5NGY3R3RCdHViWlp4NlJlY2REQUREeHVNbWZrT2RGek9rSk8yLV9RSzhnTTlXRTFpbURadWJYako4dnUwSWZrdS0yLTB5OURwRFRvSW5mRUlVdko0LU00alB1YldqMHE0WmZidTVGWWlr?oc=5",
        "label": "POSITIVE"
      },
      {
        "title": "Hologic (NASDAQ:HOLX) stock falls 3.8% in past week as three-year earnings and shareholder returns continue downward trend - simplywall.st",
        "url": "https://news.google.com/rss/articles/CBMixwFBVV95cUxOTm5tOG5Kcloxb1lIZjU4OVlEd05WYnVjUFRmcXpRcFE3MWpqdzh2X20xSXNJNW5qOHM5ZjM2UHZYaVJsM3I0Sl9pZ09IQXp4MmdCbUxKWXRtMG9fcElRZDFOemNvSDc1Qkt5T3RmRTRucmVqdGcwRXI5b1FWZkx0T0RqRDlxMEdOQTgzSC1ZaXRQZWFPSnNsXzhidThPM0V3NUliZjVpMjJOei1ybjg1YS10d1QtRjNUeGR5cVhJV09xb0VjOUlZ0gHMAUFVX3lxTE9uUmZpTDg5elFJV1puUGtoeWUtamtmY2tSYzFrNWRKUXF1Ym5oRkd6Ync5MVpzRVJ6a0FOd2J5NTdyWjlUQzY2VU1oNU9RNHNsOHRZbTd0RXkzY3AtX3lMQXhUU09Ec2lad2lfNkZISkJxM2FUZjJOY0JtR2NFRUVLQllnc0VNMGluS2cwNTlFWWdDU2xjNXN2NFVGajdobm1UV2VFbE9ETl92ZHZhUGY0ZmZrREZKRWp5eF9NSzV0aFlHTlVJcHJTdHlFeA?oc=5",
        "label": "NEGATIVE"
      },
      {
        "title": "How To Trade (HOLX) - news.stocktradersdaily.com",
        "url": "https://news.google.com/rss/articles/CBMilwFBVV95cUxQNjZIOEtIN0RnNWo0OUl3ZGZTR3NHZnM1V0RnblVsR3BHM2dvYzVPNHhkaFZxVEg0Xzh3VlR1blJlMEFBSlNxRFlLU1JtOHI4YlhmbEE5MDV5SE1CVElneFJtdjI2ekhydHFHaUFKdnhZSlRuSTNmbXJleDhkbml5b3JnVGN0U21INXVKT2thTGl1QUNmLTNz?oc=5",
        "label": "NEUTRAL"
      },
      {
        "title": "Hologic stock rises after take-private offer (HOLX:NASDAQ) - Seeking Alpha",
        "url": "https://news.google.com/rss/articles/CBMiggFBVV95cUxNWDlRV1dpUGxnd3RpVjRJQ2VJZEwwT0k5QUNKSXQ1TVRkSVVMaWY1b0FKN1A3ZXo5TDkwb3VQdlo3ckhmQS1qY2hNNnRVSGZRQjEydEQ0VlRsT2NjcGFCekUzc1VraUp5TWdiQmpRZS04cUNNRjdkaC1hWXdwR1N3MlVn?oc=5",
        "label": "POSITIVE"
      },
      {
        "title": "Here is What to Know Beyond Why Hologic, Inc. (HOLX) is a Trending Stock - sharewise",
        "url": "https://news.google.com/rss/articles/CBMi0gFBVV95cUxQLXhPTzBHZE9wa2xhaU5ZbmxEZ3UyVEpiUVFfeXg5UThhVEU5RlBNMl8xWXYxTUlsbFdFbkZsVUpick11eXBvSERMay1wWi1nRHh2R01UTVJzcTNZS2VTMDdfd2VYN3Aya2htMXNjWUd4Mi04ZHh6bm9wbGM5WnNJdjdLamtTdE0wdzNsSS1rN29ESUZZeGgwQnRMakZLaTZyMFduOUIxVFlLNlE1M2NtdW1pOG01d1EyNVNTVDl2Xy10UXVMYTJrbXdXZUY4TV83UWc?oc=5",
        "label": "NEUTRAL"
      },
      {
        "title": "HOLX vs. DGX: Which Women's Health-Focused Stock Is the Better Pick? - The Globe and Mail",
        "url": "https://news.google.com/rss/articles/CBMi5wFBVV95cUxNWEN4WjNzUW4xRm13b0ZOUDZCa3Y5b2JOV1lLNFpUODVBdDZRVjdtb3QxLTQ1YXNvMXVZSEVrV0UwMWlzZ1RfWUJqUXNoN3ZEZFc3VnhfUDhLYjh4NmtzbEpzTEZOT3ZWbnlYc09lZDlyTHhBNnBrSUY2dmNHMWtwSjNWY1lJb2ZnRENEWWRuZVpRS0xnbk5oSHBISERrOVFRRFRfT082XzktVHJWWEdhaF9GWnFLTWNpb2FiVzhKY01FWHc3UmFBY3RDOWNVT3ZJM25PSFkwdWVRY2h1SlhDNE5uTjVEREk?oc=5",
        "label": "NEUTRAL"
      },
      {
        "title": "Why Is Diagnostic Firm Hologic Stock Trading Higher On Tuesday? - Benzinga",
        "url": "https://news.google.com/rss/articles/CBMivwFBVV95cUxPdjhJOWEzNG5Pbi1tQ1NiSGhCeUc3LVlyendTS2x1SHVQM2FKSnhuNTZ3aklLWEVnOU9HWllRbHZNdi03WXF0Qzc1bXdBZi1yeUhHUzk0MXEwQlFZcDNTcElkdEkzUEpCcG5ueE94dkdsU1RXbVRzSzAyRWh3d2tVZXdXWlFhRlBuUFpNY19FVHhFNDBWMzFoUzJsY081cUxGLS1CNVRoTlFfRjdFa0pHX2RmNmVLTkRaQzVIbDBrOA?oc=5",
        "label": "NEUTRAL"
      },
      {
        "title": "Hologic shares surge on reported buyout approach - Investing.com",
        "url": "https://news.google.com/rss/articles/CBMirwFBVV95cUxQWVZvRWc1NDFJbm1QTXlFT3EyMUZybGY2UEZGUy1KWERkR0dLQ2ZEaTZCb0lWNkFIZGRQeS1kYnJZNjZkQ3hFUlhhYzh3U3FGYXQ5MG5TTEs5U2xnelFLdUhycmFHYnZsM3VxS0hROXJrSnhVVzlmWjFZQndqUXVKQzhTalNJUDdPVzRhZlVWNGgzVkFUNnNvOXRuRmp6Nk4zZTV4c0lCcUR1RGF6bkxN?oc=5",
        "label": "NEUTRAL"
      },
      {
        "title": "Needham Reiterates Hold Rating for Hologic (HOLX) | HOLX Stock News - GuruFocus",
        "url": "https://news.google.com/rss/articles/CBMipAFBVV95cUxQME9PMk9HN1VQQ2ZJVFNDR2RYbmhrNGlIekJkb09NbmRiX0M0bmpHNWFra29nS2ZYV2t2QWdoYjM0LV94QURYbkdkY2ViQjJBR3R4YjdFNU01YXZOdkRTc21DWklkUTAyb3Q2YUtoUzNCV3hENkNkUjgyaTJZWVFHOC1kV0dKdXdrTVQxWkNnY21VaWZXQjZQVENZaFd5RVVwWjFsMQ?oc=5",
        "label": "NEUTRAL"
      },
      {
        "title": "Q1 Earnings Outperformers: Hologic (NASDAQ:HOLX) And The Rest Of The Medical Devices & Supplies - Imaging, Diagnostics Stocks - Yahoo Finance",
        "url": "https://news.google.com/rss/articles/CBMijwFBVV95cUxOSFNrVTVxWXBKaTlBa1owNVR5WmY5Wmd0MTYyRFY0MEpCWi1CZ3pnb1FSQVVaYnZ6Y280Zy1ScGUyWk5LbFV6YzlIb2dUZnYwRXhUZ0N0R3VBMVRQWllMMUxJX2tWS1pKb3E3ZzYzYkhmUE5IMVVxbTZIM3BZZlBrcXVQQUR6WDJTOGNhU1R4SQ?oc=5",
        "label": "NEGATIVE"
      },
      {
        "title": "Hologic (HOLX) Stock Moves -1.08%: What You Should Know - Yahoo Finance",
        "url": "https://news.google.com/rss/articles/CBMifEFVX3lxTE9LN1dZUTl4ODlSN1VtVVdLQTRZMlhORTFFQVRUczVwWlltSzVHbjQwajZqYmJhRi15WEZPeWZsdHpqeHNLVDFxVmpiWXBDVHluN3J1c3ZfUXVsUU9ncGluWlJFZzN3aTd3U3dZNXFTbnV1bEJnSWF6NEFRQWk?oc=5",
        "label": "NEUTRAL"
      },
      {
        "title": "HOLX Stock Down 24.7% in 6 Months: Time to Cut Losses or Buy the Dip? - Yahoo Finance",
        "url": "https://news.google.com/rss/articles/CBMidEFVX3lxTE5Bc0NNd3kzYU1KdXZxMFp5cE5GNzlmUWVaaFJFSXBRV0RrM3JSSkRZenEwQk1WT2VJTkE3UktSc1BkQ0l3OHlLanRWa1dZaEFfbGQxZXBaYUpnZzhHMjhtUVJ0VGdJaE5teVlwLW02V090ZDUw?oc=5",
        "label": "NEGATIVE"
      },
      {
        "title": "Hologic Stock: Is HOLX Underperforming the Healthcare Sector? - Nasdaq",
        "url": "https://news.google.com/rss/articles/CBMijAFBVV95cUxOV2tPSTRXX3RUdjdKWGE2VWR5YXYxbUdoMmhITkpOcVAwa0YzSDRBbFhWSmhBa3JXZGtvRjZHaHZfWTBFUk9QNWRYREN5Ny1OdzA3SXZfMDhRdWRrdmh2bDZjcHFnX0stem9JQkl0eFMybW9ZaEduQzFLcjFZYzFLM3NLczYydUE5bkZFSg?oc=5",
        "label": "NEGATIVE"
      },
      {
        "title": "Why Hologic, Inc. (HOLX) Went Up On Tuesday - MSN",
        "url": "https://news.google.com/rss/articles/CBMiuwFBVV95cUxPV1FqSE5yZzlSU0J4b2trc0Q3a2xNMTBCNk8yTU9kOVJnTnI5dHM5M2h0U0pVSFlJeTBmaWMtWW1Pb2hSeEkxaGZ2WlZtNlM3YmwxSllZV1BCZXlQLXhUS2hGYmROSXFhVnQtTmUxMmpZbThVNmRQSVJ1ZW1RSnlfekE5bE9CR014X0I5Z0xfTVRmSDdySzk3QWljR25WVU54M1hWZXl2ZV9zNXd1QnVSYnJDTTVFUDItLTlr?oc=5",
        "label": "NEUTRAL"
      },
      {
        "title": "Hologic (HOLX) Surges Following Take Private Offer Report | HOLX Stock News - GuruFocus",
        "url": "https://news.google.com/rss/articles/CBMirwFBVV95cUxOdVZGZXdVSUNMNDg0bno3Szc1d0Z6Sm53b19aNDk1eTNqbjBwdGxPQlpILTA1SVdia3VGc2dfRW9rWHdDMHFWWUt2TXlYdU9KSER2cllvcGNySDBnWkVGOFBBbEgwdjBGbEFQQm5zbVBEOUh0U1VmZVlQSl9vdmxMWW03SVJJeDlCUXBGUTQ3Mkhybi13MzNOb3hyUkFjOXFVMUdoWTBGZ0ZYa2U2RDk4?oc=5",
        "label": "POSITIVE"
      },
      {
        "title": "Hologic Stock: Is Wall Street Bullish or Bearish? - Nasdaq",
        "url": "https://news.google.com/rss/articles/CBMiggFBVV95cUxOdUtTa2ZtTHhFVzM4dGVCc0t0SjlVQUVkS2Z2a2R1UFpsamdPT3dLMk1aNy1nNVFPNjJMaEcyXzFVVFNRdG5aU2ZWcmpqS1l1cTROeHBJYXB6RS1VLVRQOFRhcS1BZnpjTEhkeEl6ZUFKbjM4b2FtZll6YnlDVklqa3Nn?oc=5",
        "label": "NEUTRAL"
      },
      {
        "title": "New Product Launches to Support HOLX Stock Amid Macro Issues - Yahoo Finance",
        "url": "https://news.google.com/rss/articles/CBMiiAFBVV95cUxPa09lNnVXaUZkZzFFa09mOEttalc2dHBOTk9wSFIyajRONjM5UktsR01kRmpuOXZKeUd6VFBKaGpHSTl0NUQ1MkduMldvNTlBNms2WWo5Y1l2d3Z5WHg3M3BoWEVUNWl1aTZuTEVVMVRwbWJLc1prQloyZ0JuRFVQMld4WnNmbDBW?oc=5",
        "label": "POSITIVE"
      },
      {
        "title": "Hologic (HOLX) Shares Surge on Private Equity Interest - GuruFocus",
        "url": "https://news.google.com/rss/articles/CBMilgFBVV95cUxPRktYS25WT2JVdGpBU1JIWlFHUlV2M3ZCc09JbFlpTFNDdl9NTTRocGZ2MHo3NUZTRWZpWmlnZzdLTkNRcUxUeTBkOHhsZ3dhQzZpYmRLc2xyeEY4dXpiT2gySDhwYzJaREVYM1dyWTRuRHl0WXZPVFRiTjlSYTVHbE9tdURSOWNaSmxuYTk2a0cydnlKUGc?oc=5",
        "label": "POSITIVE"
      }
    ]
  },
  "extraction_date": "2025-05-16"
}