{
  "ticker": "LII",
  "name": "Lennox International",
  "sector": "Industrials",
  "market_cap": 21495627776.0,
  "source_list": "SP500",
  "fundamentals": {
    "PE": 26.452839,
    "PB": 25.220451,
    "EV_Revenue": 4.241,
    "ROE": 1.3148301,
    "ProfitMargin": 0.1496,
    "GrossMargin": 0.32801998,
    "DividendYield": 0.91
  },
  "technical_indicators": {
    "RSI_14": 64.34851144734114,
    "Momentum_10": 7.882318925017772,
    "MACD": 11.696735469410555,
    "BB_Percent": 0.9042689945917683,
    "SMA20_above_SMA50": 0.0
  },
  "scores": {
    "ValueScore": 0.8777872847141297,
    "QualityScore": 0.3421233352102009,
    "SignalScore": 0.5755416246395095
  },
  "volatility": 0.024078254845258,
  "beta": 1.188,
  "return_6m": -0.019325489204112,
  "analyst_rating": {
    "recommendation": "hold",
    "analyst_count": 18,
    "target_mean_price": 559.1667
  },
  "visual_data": {
    "sparkline": [
      {
        "date": "2024-12-02",
        "price": 667.46
      },
      {
        "date": "2024-12-03",
        "price": 663.96
      },
      {
        "date": "2024-12-04",
        "price": 665.53
      },
      {
        "date": "2024-12-05",
        "price": 651.33
      },
      {
        "date": "2024-12-06",
        "price": 661.12
      },
      {
        "date": "2024-12-09",
        "price": 638.79
      },
      {
        "date": "2024-12-10",
        "price": 646.5
      },
      {
        "date": "2024-12-11",
        "price": 657.48
      },
      {
        "date": "2024-12-12",
        "price": 662.0
      },
      {
        "date": "2024-12-13",
        "price": 664.5
      },
      {
        "date": "2024-12-16",
        "price": 668.03
      },
      {
        "date": "2024-12-17",
        "price": 657.59
      },
      {
        "date": "2024-12-18",
        "price": 638.32
      },
      {
        "date": "2024-12-19",
        "price": 619.88
      },
      {
        "date": "2024-12-20",
        "price": 628.28
      },
      {
        "date": "2024-12-23",
        "price": 625.06
      },
      {
        "date": "2024-12-24",
        "price": 631.13
      },
      {
        "date": "2024-12-26",
        "price": 629.64
      },
      {
        "date": "2024-12-27",
        "price": 620.03
      },
      {
        "date": "2024-12-30",
        "price": 613.99
      },
      {
        "date": "2024-12-31",
        "price": 609.3
      },
      {
        "date": "2025-01-02",
        "price": 604.52
      },
      {
        "date": "2025-01-03",
        "price": 612.71
      },
      {
        "date": "2025-01-06",
        "price": 609.98
      },
      {
        "date": "2025-01-07",
        "price": 611.29
      },
      {
        "date": "2025-01-08",
        "price": 625.57
      },
      {
        "date": "2025-01-10",
        "price": 610.06
      },
      {
        "date": "2025-01-13",
        "price": 618.51
      },
      {
        "date": "2025-01-14",
        "price": 627.71
      },
      {
        "date": "2025-01-15",
        "price": 630.76
      },
      {
        "date": "2025-01-16",
        "price": 642.86
      },
      {
        "date": "2025-01-17",
        "price": 647.46
      },
      {
        "date": "2025-01-21",
        "price": 663.59
      },
      {
        "date": "2025-01-22",
        "price": 663.31
      },
      {
        "date": "2025-01-23",
        "price": 666.93
      },
      {
        "date": "2025-01-24",
        "price": 662.63
      },
      {
        "date": "2025-01-27",
        "price": 655.99
      },
      {
        "date": "2025-01-28",
        "price": 662.59
      },
      {
        "date": "2025-01-29",
        "price": 604.33
      },
      {
        "date": "2025-01-30",
        "price": 606.54
      },
      {
        "date": "2025-01-31",
        "price": 592.42
      },
      {
        "date": "2025-02-03",
        "price": 582.93
      },
      {
        "date": "2025-02-04",
        "price": 578.37
      },
      {
        "date": "2025-02-05",
        "price": 585.03
      },
      {
        "date": "2025-02-06",
        "price": 585.38
      },
      {
        "date": "2025-02-07",
        "price": 575.14
      },
      {
        "date": "2025-02-10",
        "price": 583.13
      },
      {
        "date": "2025-02-11",
        "price": 602.35
      },
      {
        "date": "2025-02-12",
        "price": 608.72
      },
      {
        "date": "2025-02-13",
        "price": 619.95
      },
      {
        "date": "2025-02-14",
        "price": 622.2
      },
      {
        "date": "2025-02-18",
        "price": 636.03
      },
      {
        "date": "2025-02-19",
        "price": 651.16
      },
      {
        "date": "2025-02-20",
        "price": 641.38
      },
      {
        "date": "2025-02-21",
        "price": 613.96
      },
      {
        "date": "2025-02-24",
        "price": 609.7
      },
      {
        "date": "2025-02-25",
        "price": 618.76
      },
      {
        "date": "2025-02-26",
        "price": 622.97
      },
      {
        "date": "2025-02-27",
        "price": 602.25
      },
      {
        "date": "2025-02-28",
        "price": 601.05
      },
      {
        "date": "2025-03-03",
        "price": 586.98
      },
      {
        "date": "2025-03-04",
        "price": 572.97
      },
      {
        "date": "2025-03-05",
        "price": 588.07
      },
      {
        "date": "2025-03-06",
        "price": 583.9
      },
      {
        "date": "2025-03-07",
        "price": 606.61
      },
      {
        "date": "2025-03-10",
        "price": 604.62
      },
      {
        "date": "2025-03-11",
        "price": 566.17
      },
      {
        "date": "2025-03-12",
        "price": 569.64
      },
      {
        "date": "2025-03-13",
        "price": 558.51
      },
      {
        "date": "2025-03-14",
        "price": 574.92
      },
      {
        "date": "2025-03-17",
        "price": 589.16
      },
      {
        "date": "2025-03-18",
        "price": 581.37
      },
      {
        "date": "2025-03-19",
        "price": 591.43
      },
      {
        "date": "2025-03-20",
        "price": 578.77
      },
      {
        "date": "2025-03-21",
        "price": 569.55
      },
      {
        "date": "2025-03-24",
        "price": 586.25
      },
      {
        "date": "2025-03-25",
        "price": 587.91
      },
      {
        "date": "2025-03-26",
        "price": 578.88
      },
      {
        "date": "2025-03-27",
        "price": 577.32
      },
      {
        "date": "2025-03-28",
        "price": 553.05
      },
      {
        "date": "2025-03-31",
        "price": 560.83
      },
      {
        "date": "2025-04-01",
        "price": 564.83
      },
      {
        "date": "2025-04-02",
        "price": 574.53
      },
      {
        "date": "2025-04-03",
        "price": 546.82
      },
      {
        "date": "2025-04-04",
        "price": 531.3
      },
      {
        "date": "2025-04-07",
        "price": 524.25
      },
      {
        "date": "2025-04-08",
        "price": 510.52
      },
      {
        "date": "2025-04-09",
        "price": 561.17
      },
      {
        "date": "2025-04-10",
        "price": 550.29
      },
      {
        "date": "2025-04-11",
        "price": 554.42
      },
      {
        "date": "2025-04-14",
        "price": 558.64
      },
      {
        "date": "2025-04-15",
        "price": 557.2
      },
      {
        "date": "2025-04-16",
        "price": 547.86
      },
      {
        "date": "2025-04-17",
        "price": 556.15
      },
      {
        "date": "2025-04-21",
        "price": 541.02
      },
      {
        "date": "2025-04-22",
        "price": 558.93
      },
      {
        "date": "2025-04-23",
        "price": 508.76
      },
      {
        "date": "2025-04-24",
        "price": 524.05
      },
      {
        "date": "2025-04-25",
        "price": 527.31
      },
      {
        "date": "2025-04-28",
        "price": 531.17
      },
      {
        "date": "2025-04-29",
        "price": 534.91
      },
      {
        "date": "2025-04-30",
        "price": 546.75
      },
      {
        "date": "2025-05-01",
        "price": 557.02
      },
      {
        "date": "2025-05-02",
        "price": 561.51
      },
      {
        "date": "2025-05-05",
        "price": 562.92
      },
      {
        "date": "2025-05-06",
        "price": 566.68
      },
      {
        "date": "2025-05-07",
        "price": 567.97
      },
      {
        "date": "2025-05-08",
        "price": 576.38
      },
      {
        "date": "2025-05-09",
        "price": 573.7
      },
      {
        "date": "2025-05-12",
        "price": 595.73
      },
      {
        "date": "2025-05-13",
        "price": 602.34
      },
      {
        "date": "2025-05-14",
        "price": 591.37
      },
      {
        "date": "2025-05-15",
        "price": 594.22
      },
      {
        "date": "2025-05-16",
        "price": 605.77
      },
      {
        "date": "2025-05-19",
        "price": 604.47
      },
      {
        "date": "2025-05-20",
        "price": 597.05
      },
      {
        "date": "2025-05-21",
        "price": 569.95
      },
      {
        "date": "2025-05-22",
        "price": 574.6
      },
      {
        "date": "2025-05-23",
        "price": 567.16
      },
      {
        "date": "2025-05-27",
        "price": 579.22
      },
      {
        "date": "2025-05-28",
        "price": 568.24
      },
      {
        "date": "2025-05-29",
        "price": 569.5
      },
      {
        "date": "2025-05-30",
        "price": 564.45
      }
    ],
    "current_price_data": {
      "price": 564.45,
      "change": -5.05,
      "percent_change": -0.89
    }
  },
  "news_sentiment": {
    "summary": "Les titres concernent Lennox International, une entreprise cot\u00e9e du secteur de l'industrie. Il y a plusieurs nouvelles qui rel\u00e8vent d'int\u00e9r\u00eat pour les investisseurs francophones.\n\nUne ancienne chef d'entreprise de Trading Report a rejoint le conseil d'administration de Lennox. Cela peut \u00eatre consid\u00e9r\u00e9 comme un signe positif car il apporte une exp\u00e9rience de gestion de dirigeants.\n\nLennox a annonc\u00e9 une augmentation de son dividende de 13% pour la prochaine ann\u00e9e. Cela est un signe positif pour les investisseurs qui recherchent des revenus r\u00e9guliers.",
    "sentiment_score": 0.3,
    "label": "POSITIVE",
    "positive_ratio": 0.35,
    "neutral_ratio": 0.6,
    "negative_ratio": 0.05,
    "bullet_positive_count": 0,
    "bullet_negative_count": 0,
    "headlines": [
      {
        "title": "(LII) Trading Report - news.stocktradersdaily.com",
        "url": "https://news.google.com/rss/articles/CBMimAFBVV95cUxOV0VKbEJIOHpid0ZRWmpxbjJxek5qaUFjUjNLTHFLSGpTZ0RkMElteVRRTDRjOXpkWEdsdTRNeE1iX2duNi1ERkM3bmZIcmVhT0VhQ1VGQUZITHpTa1locGtQOFotX0czbm1vQ1l4cExEYXdtOGtVa1VlT0Z4MVlINDBNYTZVMFhLMWF0QjZVUm90eXFGdFBSeQ?oc=5",
        "label": "NEUTRAL"
      },
      {
        "title": "Former Otis Americas Chief Joins Lennox Board: MIT Grad Brings 23 Years of Cummins Leadership - Stock Titan",
        "url": "https://news.google.com/rss/articles/CBMimgFBVV95cUxNVFFRZExvaGFLbXlyT2N3WmRuYThONzE1aWZVUUdnYnFPVmwwY1VacVhPZ24tVDZ2UW03ZnJ6UnNPQXloWGd2UVYtRmp2b0steEdvc2xMRUlUbjdaMDQ2VWdSMXpfMTlRYW52TjdWa3Z1UXlwQmJldGhDVVlncFd1R2pBNkZ1QmY0d2gxMDRMc00tOE1XU3FVc25B?oc=5",
        "label": "NEUTRAL"
      },
      {
        "title": "LII Q1 Earnings Call: Tariff Impacts and Product Transitions Shape Outlook - Yahoo Finance",
        "url": "https://news.google.com/rss/articles/CBMifkFVX3lxTE9ERmZTcEEyRlRLQ3NtSjVrUzhaRFdNOUJ1N0NMN1d3eGVpekJpZTJwQkxwMDg1N19hcjF5V0hzRTU1TzBpaC1mQ3MyT081aVhad2pTV09tTnFZbVRGQWJnUTF5QWxXVndSQ2FvMnNXMGZGZVQwV2NRd3JwTUdFUQ?oc=5",
        "label": "NEUTRAL"
      },
      {
        "title": "Lennox (LII) Forms Joint Venture with Ariston Group in Water Heating Sector | LII Stock News - GuruFocus",
        "url": "https://news.google.com/rss/articles/CBMixwFBVV95cUxQZnpPbmlUWDViY2xRUTRKVElVc3FyT01aWlltY1lGX0t4Z2tTMjFVbzMwdDhvc01ES2FBNlBHRmI1Q1pXZHpUemdJSDdVX0w2MFNsMC1sRkprZFNtd1NuOGd6TXltS0k2ZGY2aWY4NmRHNWxLX1RmTWx2V2R6djR1ZGtvT2VqMXdjSmhwSGFPTXhDT0xCeVR6SjdUcXZrZEFsWnNBR3pjd2h5U21BN08zSjVqOEhzaENnbG1SeGpQdERZUlNLWXlZ?oc=5",
        "label": "NEUTRAL"
      },
      {
        "title": "Lennox International (NYSE:LII) Has Announced That It Will Be Increasing Its Dividend To $1.30 - simplywall.st",
        "url": "https://news.google.com/rss/articles/CBMi2wFBVV95cUxQUi1WQ3NUaWhkMFlITlBPdk9vMF9HMWtlX1FfR1AzZWdPZDk3NjJEMUIxSU53TmZ1RGhvWW42VTBXNFBRMWpmcUNldHRBNG1uVVFEWHpRQ0FLNjZMMVhIbjV1Ty04dHdITnJYczVacTJNN1lGXzNQcjlmM2E1Q25pRUcyM0NyVml3M24zVFpwNk9CYUJySlJfRk54eThYS2RqSkJnUlFzaHJDRkxVRHRNMVZ3dENsendTb3c3YlByb3RrTkJxS05KYWtQRzJPQzRKdTA2dFg5eGNkVGfSAeABQVVfeXFMT1B3Z1F6NEYtaVYyZnJVUkRaYlpBZnJjaDZxT2FMSlZqenJYMzhjdExrOTRwbVU5ajlQeThUUzY3NnVmZ1pLWXlwaEwwXzQxZE15LW5nT21PZEd5NmdCUmVwam53cm8xbHZFYW5CTXM4cXp2ZGh2dzBpbjE4ZGpVTWt2SjVuMF9aT3ZNT3kxWXhDcThvS3Vicms2UUtyV3F1d0ZTM3dJckh5YXdJX3VodUUtR2pyWUc0NFRCUXBfX2FrMS02ZFdIZ1NXVnZDOTJOeThpWDFwYmRsakoxMTNES0k?oc=5",
        "label": "POSITIVE"
      },
      {
        "title": "Lennox International Elects Tracy A. Embree to Board - TipRanks",
        "url": "https://news.google.com/rss/articles/CBMipgFBVV95cUxPQUlFQ1RHd2p3VjNiVVJxZ2Z2cXNrTzMxcEM2U2JzRVFrbU5LZWJ1MDdJVVFmdmNVRUVDdXVORjhEaWwwT0d3RDVyY3pxNUY5bjVIeGdSUFIwY3hWWVBGRHhyQ3lKWW05Y1dqZnlaeDRmeTY2RWtJTW9YaGV1bzI3dnN4cFp2c1R3UVV3eHB2RjB6Z0VSTHRZcnhVb1V3dl82cXYxSGl3?oc=5",
        "label": "NEUTRAL"
      },
      {
        "title": "Lennox Increases Quarterly Dividend and Stock Repurchase Authorization - PR Newswire",
        "url": "https://news.google.com/rss/articles/CBMixAFBVV95cUxQQTVVWmFIWWNfZnJkaEhCcEdvSXBkRHdWV0VBdFFHTkdnWHBIakVzdURrbFgtc0FJa1F0eEp4LW9uVHNKUWxBN053TS1lV1FhZVNKMVpzdlFZLTJnalJ1dTBKQ0tKTWo2enEzSUxOdzlmaWNKbS0yZUVlQkIwOVBSR2xqSUZoT1lDRUpoUFZGLUxjcDRSUW5vSUNkM1ZNUGI2Ykw1aThSMTJtWWJBM2RmMXZDdUNFU181X2NxZnUtbkJQRnF0?oc=5",
        "label": "NEUTRAL"
      },
      {
        "title": "Lennox International Stock: Priced For Modest Growth (NYSE:LII) - Seeking Alpha",
        "url": "https://news.google.com/rss/articles/CBMijwFBVV95cUxOdGQ1SVVPREUwNTNlSUxtZm9uTFI3TzkwMFZsel84eXRCdk9JRzAxSkZCZHNWNngyNkEyLWJMRzI1TUJjd3JKTjllY29reWN6OGNmM2VVN3FxMy1sM0VoSTRvcUdPaGZWZ2Z1ZHBnc1FQZXp0VHp6cldodVViTFA3MF9DWEg2Rk5pbjBvUF92VQ?oc=5",
        "label": "NEUTRAL"
      },
      {
        "title": "Lennox Forms Strategic Joint Venture: 50/50 Split With Ariston to Dominate North American Water Heater Market - Stock Titan",
        "url": "https://news.google.com/rss/articles/CBMiuAFBVV95cUxQelptdkhmVFBwaEtkSmM4VlZvTkJHRk94am5rQXBic2liNGpWZFVrR1BoenVkbHJtYTk5a09mbW1UcEhiSnlHX1NMV1dIQXNVclYxR0lyR3lnY3VSYkxJOFAtX3ljWW5kODA3VHRMdmFnZlpjOUxSSGFHa3FENTdndTc4TmJsX1dmbEhhNVYtR3VzeEs1cmJSeVZWLUVFb3AtZHZkTW41UXYwOTQ3bG9UbEktZDMyT1Jy?oc=5",
        "label": "POSITIVE"
      },
      {
        "title": "Lennox Appoints Tracy Embree to Board of Directors | LII Stock News - GuruFocus",
        "url": "https://news.google.com/rss/articles/CBMiqAFBVV95cUxOclBicFlGLVNnX2JHQnhleWJXelJxWnE4U1FTenZNRFVwM3hjd1NFYWpJVXFvSDlud09VZERNd1hJdm5ZTEVMT2M4Wkl5Rzd1WUZGXy1YTXNvR1pqOFhmb0FieklFLXR2ZmtuakdYREF6SlJzRmM0UVRvRUZ0RFVaUFdUbkRuYUZWUmdZbmlfcjFyZXd1TXJ2OVh6dDRiYnk0QTA4WHljSE8?oc=5",
        "label": "NEUTRAL"
      },
      {
        "title": "Why Lennox (LII) Shares Are Sliding Today - Yahoo Finance",
        "url": "https://news.google.com/rss/articles/CBMigAFBVV95cUxOSm43eENxZWZieThTempzb2ktWk5YdWwxMmtDbXdmZ25iNFVEa3pFSjU2NmVsNjJaazZDQVhoNHZQelZCTXM3X2Y1eHkyRDFGOTlWLUxLVV9uX0xBZ3RSNnFFX21qUFN5QmdLLVJ2d0JaeWtWTkhJcUdKaWJDUzJLdQ?oc=5",
        "label": "NEGATIVE"
      },
      {
        "title": "Lennox International's (NYSE:LII) 28% CAGR outpaced the company's earnings growth over the same five-year period - simplywall.st",
        "url": "https://news.google.com/rss/articles/CBMi1wFBVV95cUxOWlFCbTd3blJTSFJUdEJSRUFiSDQ3dGt2NDNadWY4dXhUdXR6a0Fqdm9kNmVmNjgtWmlTbUZkdzZGelM2NThFbGp1clU2N2F0b24zOVkxZF9kRDVlOUZwaERrN0V0UVRNQl9UV2dUZFQ2OG1tckZjV21za1VjTGh0VEdvc0NTQy11emoxTWphbFBYcTRLOFRSeXBqaXJlZWt6THdfTXNYRmJpQ0tubkVsRDVsNUFxYTR2NXJaYXJmYjdUZV9rdkxaWmwwQ0xVNm5jQnJjcmpsVdIB3AFBVV95cUxPellDQVF6elBabmxHQ1lDZk9RMWVzUFVKOWs3TzROdm5keG16Z056aldtZ2J6N2hGVjNDX3hvY3BJcGtoSWhLWTBtUTVfSU96N0d1T2NhUklIamRYMlNGOGNEdGI2MkRiRTdpM1B3S3ZtMHNSU0Q0U2E0TUU2YVhJV0tlWmxTU0FaY283elJSdWV0NnBMRXFKRlVJTmhhMVJlODJJR2VneTZsSzlscjBCQ1FCX1JzMDVzM1JMVmJvZlFNTG16eTdFaFVoOWI2Z2xrRGhHSFNGYUk3OS1r?oc=5",
        "label": "POSITIVE"
      },
      {
        "title": "Lennox Unveils Massive $1B Stock Buyback Program and Double-Digit Dividend Hike - Stock Titan",
        "url": "https://news.google.com/rss/articles/CBMirwFBVV95cUxNQS1pNXdBMGs4Rlh0V2xrYWVLbHBwYVBJSGtSMU00YU5SNzVLV2liT2tDTE9tUWtPaVRpMnVNemJxSGprOTQ3cWJXWjB4N21EbTdJeGxiWEpGY24xank1ZEpmYktseWRPWktZeXYtcW9DWDFabngtSGo1X0h1b3J6OWtsMXRQQkd4WlNQTGZucHNvTGpkaTQwSXlGSXJ5S2NXTkpDT3g0Z05MUGNsUUZn?oc=5",
        "label": "POSITIVE"
      },
      {
        "title": "Lennox (LII) Announces 13% Dividend Increase to $1.30 | LII Stock News - GuruFocus",
        "url": "https://news.google.com/rss/articles/CBMipAFBVV95cUxQTVcyazFpN19rQ2xwNTBwaG5tQVNVMVh5RkotTkNOZ1BiVll5ZXgtN1ZZWnVaUjJRNWdPZl9tWVliTjg4aUNNcEIxLUd1NEhiMXR3Mlk0N2lQdE9UMjlsN1RFczV4bGdBOXFJQktOcGxjRTBMM194ZFBrdVJLdXdGZkNwal9hVklhZXhNZXhMUC1MQU9nUUw5SVh1LW1WOXR6aXFKeQ?oc=5",
        "label": "POSITIVE"
      },
      {
        "title": "Is Lennox International Inc. (NYSE:LII) a Small-Cap Manufacturing Stock Hedge Funds Are Buying? - Yahoo Finance",
        "url": "https://news.google.com/rss/articles/CBMihgFBVV95cUxON3lRSjZnM050ZEFTc3lBTmxSOU1ZTTZ5UWQ4Z1dRc2d6ZUFRRTNzZkJ3YkZQRXJXOFB5SVU5OUhIalJueHZmeVkxQ1lvbDhBUGN1M1F3S0ptN05iOWlMZU5SRTIzSUI2Z3NPdDVabGtHRld1U01udmVVZWlsZXJFVzF0Sm9RQQ?oc=5",
        "label": "NEUTRAL"
      },
      {
        "title": "Lennox Increases Quarterly Dividend and Stock Repurchase Authorization | LII Stock News - GuruFocus",
        "url": "https://news.google.com/rss/articles/CBMiwwFBVV95cUxQY3FuMUFza3FFYmJaRnIzaGVEOG1yVWlBNVVrVEM3TnBjTVQ3b3B1cVFyS0xfRG04OEtOeVlUNFFMQ3dhb09zMC1SOXZyb2FYOG55S2d6OC1pdEFEemlzR1J0d1BVTGZXY0RRa3ZleF9vS3RTZG5hVWZQdmgxLWFIQ3lIaWJmR1RYRTBuM3hFQTBRSW5SdHZRaHpoaFBhODNUTFQwRDl6UjFuM3ZvSF85aEpRVDdiZTZxOXYya3JTcGg1Y0k?oc=5",
        "label": "NEUTRAL"
      },
      {
        "title": "Lennox Maintains Strong $1.15 Dividend: Key Dates and Payment Details Revealed - Stock Titan",
        "url": "https://news.google.com/rss/articles/CBMihgFBVV95cUxNYzFXWDRNcnpwUGdOaXBMVUtoRXVHN1poeGtNcjBrV3ZheUxWdjFNVmtvUlZGdVdCSUtMTGN2aDdPVUczTERyTVIxQkV1eE9sRHB1d1h5MUNuYTA0OG9sMjd3aFYtVV9fMTJucFQ1azV4SnplZ2hRRXJCRllrNndMbVd2WlBCQQ?oc=5",
        "label": "NEUTRAL"
      },
      {
        "title": "Lennox Q1 Earnings: Home Solutions Surges 7% While Building Segment Faces Pressure - Stock Titan",
        "url": "https://news.google.com/rss/articles/CBMiigFBVV95cUxPT2R4c2FpdG5vem13MTRIQTZURWVJYjFnWHN0bzl2ZjZicEhyX2o1XzhaeE42SWlPRVg5enNmOUlXcTFtdjhVR2dkMTZjV1Etc1BZQzg0ZnJTaWxTai1fSDMxSXVQUjM3RnE4ZTFuWnhnNUx3R0NfLWFPcEdBMXVxMXhvUmlPY3o3ckE?oc=5",
        "label": "POSITIVE"
      },
      {
        "title": "Lennox (LII) Price Target Boosted by Mizuho to $595 | LII Stock News - GuruFocus",
        "url": "https://news.google.com/rss/articles/CBMipAFBVV95cUxOTldmYnBPRDhMakRIOUJiYm41cXpETWF5MWxGOWdkZkMtQmREZy1OZUpacm5iSHZmVjVoYnZUMUszUG00N29EOWRDRVlxaEJ2d3d4cVBoeWZZSkE1NmlEQ2RHOUxjY3NJWEhiTDZoWWhPRTluczRQRWV2NkJHcHAxdTd4RkJTZTZjaTRKMFU1LXptQ2ZEQm55ZHpPaWNtYjJKRU04ag?oc=5",
        "label": "POSITIVE"
      },
      {
        "title": "Lennox (LII) Ups Share Repurchase Program by $1 Billion | LII Stock News - GuruFocus",
        "url": "https://news.google.com/rss/articles/CBMiqgFBVV95cUxOZXBnUlh6UDZqa2EzMFRFRTJXXzl0Y3o1UXZYdTFkb2hEWG0yNGcwclViZEwzdV9ON2xidlBkWE1rX1pJbG53dlRQZmY2aWVWa3dNZHh3cVFTWEUtdWNGX2g0NTJ0b3BlMVdaVzhLZTJoVWsxbXc3LTNUNnU5dVRGSTFDamdxU0Z0NVFOTUxiSUhTUTFKRXFmMWdtMTlBN3kydjRfbTJoWjZFQQ?oc=5",
        "label": "NEUTRAL"
      }
    ]
  },
  "extraction_date": "2025-05-16"
}